cornerstone/__init__.py
cornerstone-0.5.1.dist-info/LICENSE
cornerstone-0.5.1.dist-info/METADATA
cornerstone-0.5.1.dist-info/WHEEL
cornerstone-0.5.1.dist-info/top_level.txt
cornerstone-0.5.1.dist-info/RECORD
