Metadata-Version: 2.1
Name: cornerstone
Version: 0.5.1
Summary: Basic github repository setup for python projects.
Home-page: https://github.com/KraYmer/cornerstone
Author: Fabrice Laporte
Author-email: kraymer@gmail.com
License: MIT
Platform: ALL
Classifier: Programming Language :: Python
Classifier: License :: OSI Approved :: MIT License
Requires-Python: >=3.6
License-File: LICENSE
Requires-Dist: pytest
Provides-Extra: test
Requires-Dist: coverage (>5) ; extra == 'test'
Requires-Dist: pytest (>=6) ; extra == 'test'
Requires-Dist: tox (>=3) ; extra == 'test'
